niaautoarm/__init__.py
niaautoarm/armoptimizer.py
niaautoarm/autoarmproblem.py
niaautoarm/logger.py
niaautoarm/pipeline.py
niaautoarm/preprocessing.py
niaautoarm/stats.py
niaautoarm/utils.py
niaautoarm-0.1.1.dist-info/LICENSE
niaautoarm-0.1.1.dist-info/METADATA
niaautoarm-0.1.1.dist-info/WHEEL
niaautoarm-0.1.1.dist-info/RECORD
