Metadata-Version: 2.1
Name: NiaAutoARM
Version: 0.1.1
Summary: Automated generation and evaluation of Association Rule Mining pipelines
Home-page: https://github.com/firefly-cpp/NiaAutoARM
Keywords: association rule mining,computational intelligence,data mining,datasets,optimization
Author: Uroš Mlakar
Author-email: uros.mlakar@um.si
Requires-Python: >=3.9,<4.0
Classifier: Programming Language :: Python :: 3
Classifier: Programming Language :: Python :: 3.9
Classifier: Programming Language :: Python :: 3.10
Classifier: Programming Language :: Python :: 3.11
Classifier: Programming Language :: Python :: 3.12
Requires-Dist: niaarm (>=0.3.12,<0.4.0)
Requires-Dist: niapy (>=2.0.5,<3.0.0)
Requires-Dist: pandas (>=2.1.1,<3.0.0)
Project-URL: Repository, https://github.com/firefly-cpp/NiaAutoARM
